compresslib/__init__.py
compresslib/algorithms/__init__.py
compresslib/algorithms/huffman.py
compresslib/algorithms/lzw.py
compresslib/base/__init__.py
compresslib/base/abstract.py
compresslib/base/enums.py
compresslib/base/metric_model.py
compresslib/build/__init__.py
compresslib/build/huff_build.py
compresslib/main.py
compresslib/utils/__init__.py
compresslib/utils/path_utils.py
compresslib/utils/url.py
compresslib-0.1.2.dist-info/entry_points.txt
compresslib-0.1.2.dist-info/METADATA
compresslib-0.1.2.dist-info/WHEEL
compresslib-0.1.2.dist-info/RECORD
