Metadata-Version: 2.1
Name: compresslib
Version: 0.1.2
Summary: 
Author: John Smith
Author-email: john@example.com
Requires-Python: >=3.10,<4.0
Classifier: Programming Language :: Python :: 3
Classifier: Programming Language :: Python :: 3.10
Classifier: Programming Language :: Python :: 3.11
Classifier: Programming Language :: Python :: 3.12
Requires-Dist: pydantic (>=2.7.4,<3.0.0)
Requires-Dist: typer (>=0.12.3,<0.13.0)
